<cidades>
<cidade>
<idcidade>9546</idcidade>
<nome>Aguiarnopolis</nome>
<idestado>27</idestado>
</cidade>
<cidade>
<idcidade>9547</idcidade>
<nome>Alianca do Tocantins</nome>
<idestado>27</idestado>
</cidade>
<cidade>
<idcidade>9548</idcidade>
<nome>Almas</nome>
<idestado>27</idestado>
</cidade>
<cidade>
<idcidade>9549</idcidade>
<nome>Alvorada</nome>
<idestado>27</idestado>
</cidade>
<cidade>
<idcidade>9550</idcidade>
<nome>Anajanopolis</nome>
<idestado>27</idestado>
</cidade>
<cidade>
<idcidade>9551</idcidade>
<nome>Ananas</nome>
<idestado>27</idestado>
</cidade>
<cidade>
<idcidade>9552</idcidade>
<nome>Angico</nome>
<idestado>27</idestado>
</cidade>
<cidade>
<idcidade>9553</idcidade>
<nome>Aparecida do Rio Negro</nome>
<idestado>27</idestado>
</cidade>
<cidade>
<idcidade>9554</idcidade>
<nome>Apinaje</nome>
<idestado>27</idestado>
</cidade>
<cidade>
<idcidade>9555</idcidade>
<nome>Aragacui</nome>
<idestado>27</idestado>
</cidade>
<cidade>
<idcidade>9556</idcidade>
<nome>Aragominas</nome>
<idestado>27</idestado>
</cidade>
<cidade>
<idcidade>9557</idcidade>
<nome>Araguacema</nome>
<idestado>27</idestado>
</cidade>
<cidade>
<idcidade>9558</idcidade>
<nome>Araguacu</nome>
<idestado>27</idestado>
</cidade>
<cidade>
<idcidade>9559</idcidade>
<nome>Araguaina</nome>
<idestado>27</idestado>
</cidade>
<cidade>
<idcidade>9560</idcidade>
<nome>Araguana</nome>
<idestado>27</idestado>
</cidade>
<cidade>
<idcidade>9561</idcidade>
<nome>Araguatins</nome>
<idestado>27</idestado>
</cidade>
<cidade>
<idcidade>9562</idcidade>
<nome>Arapoema</nome>
<idestado>27</idestado>
</cidade>
<cidade>
<idcidade>9563</idcidade>
<nome>Arraias</nome>
<idestado>27</idestado>
</cidade>
<cidade>
<idcidade>9564</idcidade>
<nome>Augustinopolis</nome>
<idestado>27</idestado>
</cidade>
<cidade>
<idcidade>9565</idcidade>
<nome>Aurora do Tocantins</nome>
<idestado>27</idestado>
</cidade>
<cidade>
<idcidade>9566</idcidade>
<nome>Axixa do Tocantins</nome>
<idestado>27</idestado>
</cidade>
<cidade>
<idcidade>9567</idcidade>
<nome>Babaculandia</nome>
<idestado>27</idestado>
</cidade>
<cidade>
<idcidade>9568</idcidade>
<nome>Bandeirantes do Tocantins</nome>
<idestado>27</idestado>
</cidade>
<cidade>
<idcidade>9569</idcidade>
<nome>Barra do Grota</nome>
<idestado>27</idestado>
</cidade>
<cidade>
<idcidade>9570</idcidade>
<nome>Barra do Ouro</nome>
<idestado>27</idestado>
</cidade>
<cidade>
<idcidade>9571</idcidade>
<nome>Barrolandia</nome>
<idestado>27</idestado>
</cidade>
<cidade>
<idcidade>9572</idcidade>
<nome>Bernardo Sayao</nome>
<idestado>27</idestado>
</cidade>
<cidade>
<idcidade>9573</idcidade>
<nome>Bom Jesus do Tocantins</nome>
<idestado>27</idestado>
</cidade>
<cidade>
<idcidade>9574</idcidade>
<nome>Brasilandia</nome>
<idestado>27</idestado>
</cidade>
<cidade>
<idcidade>9575</idcidade>
<nome>Brasilandia do Tocantins</nome>
<idestado>27</idestado>
</cidade>
<cidade>
<idcidade>9576</idcidade>
<nome>Brejinho de Nazare</nome>
<idestado>27</idestado>
</cidade>
<cidade>
<idcidade>9577</idcidade>
<nome>Buriti do Tocantins</nome>
<idestado>27</idestado>
</cidade>
<cidade>
<idcidade>9578</idcidade>
<nome>Cachoeirinha</nome>
<idestado>27</idestado>
</cidade>
<cidade>
<idcidade>9579</idcidade>
<nome>Campos Lindos</nome>
<idestado>27</idestado>
</cidade>
<cidade>
<idcidade>9580</idcidade>
<nome>Cana Brava</nome>
<idestado>27</idestado>
</cidade>
<cidade>
<idcidade>9581</idcidade>
<nome>Cariri do Tocantins</nome>
<idestado>27</idestado>
</cidade>
<cidade>
<idcidade>9582</idcidade>
<nome>Carmolandia</nome>
<idestado>27</idestado>
</cidade>
<cidade>
<idcidade>9583</idcidade>
<nome>Carrasco Bonito</nome>
<idestado>27</idestado>
</cidade>
<cidade>
<idcidade>9584</idcidade>
<nome>Cartucho</nome>
<idestado>27</idestado>
</cidade>
<cidade>
<idcidade>9585</idcidade>
<nome>Caseara</nome>
<idestado>27</idestado>
</cidade>
<cidade>
<idcidade>9586</idcidade>
<nome>Centenario</nome>
<idestado>27</idestado>
</cidade>
<cidade>
<idcidade>9587</idcidade>
<nome>Chapada da Areia</nome>
<idestado>27</idestado>
</cidade>
<cidade>
<idcidade>9588</idcidade>
<nome>Chapada da Natividade</nome>
<idestado>27</idestado>
</cidade>
<cidade>
<idcidade>9589</idcidade>
<nome>Cocalandia</nome>
<idestado>27</idestado>
</cidade>
<cidade>
<idcidade>9590</idcidade>
<nome>Cocalinho</nome>
<idestado>27</idestado>
</cidade>
<cidade>
<idcidade>9591</idcidade>
<nome>Colinas do Tocantins</nome>
<idestado>27</idestado>
</cidade>
<cidade>
<idcidade>9592</idcidade>
<nome>Colmeia</nome>
<idestado>27</idestado>
</cidade>
<cidade>
<idcidade>9593</idcidade>
<nome>Combinado</nome>
<idestado>27</idestado>
</cidade>
<cidade>
<idcidade>9594</idcidade>
<nome>Conceicao do Tocantins</nome>
<idestado>27</idestado>
</cidade>
<cidade>
<idcidade>9595</idcidade>
<nome>Correinha</nome>
<idestado>27</idestado>
</cidade>
<cidade>
<idcidade>9596</idcidade>
<nome>Couto de Magalhaes</nome>
<idestado>27</idestado>
</cidade>
<cidade>
<idcidade>9597</idcidade>
<nome>Craolandia</nome>
<idestado>27</idestado>
</cidade>
<cidade>
<idcidade>9598</idcidade>
<nome>Cristalandia</nome>
<idestado>27</idestado>
</cidade>
<cidade>
<idcidade>9599</idcidade>
<nome>Crixas</nome>
<idestado>27</idestado>
</cidade>
<cidade>
<idcidade>9600</idcidade>
<nome>Crixas do Tocantins</nome>
<idestado>27</idestado>
</cidade>
<cidade>
<idcidade>9601</idcidade>
<nome>Darcinopolis</nome>
<idestado>27</idestado>
</cidade>
<cidade>
<idcidade>9602</idcidade>
<nome>Dianopolis</nome>
<idestado>27</idestado>
</cidade>
<cidade>
<idcidade>9603</idcidade>
<nome>Divinopolis do Tocantins</nome>
<idestado>27</idestado>
</cidade>
<cidade>
<idcidade>9604</idcidade>
<nome>Dois Irmaos do Tocantins</nome>
<idestado>27</idestado>
</cidade>
<cidade>
<idcidade>9605</idcidade>
<nome>Duere</nome>
<idestado>27</idestado>
</cidade>
<cidade>
<idcidade>9606</idcidade>
<nome>Escondido</nome>
<idestado>27</idestado>
</cidade>
<cidade>
<idcidade>9607</idcidade>
<nome>Esperantina</nome>
<idestado>27</idestado>
</cidade>
<cidade>
<idcidade>9608</idcidade>
<nome>Fatima</nome>
<idestado>27</idestado>
</cidade>
<cidade>
<idcidade>9609</idcidade>
<nome>Figueiropolis</nome>
<idestado>27</idestado>
</cidade>
<cidade>
<idcidade>9610</idcidade>
<nome>Filadelfia</nome>
<idestado>27</idestado>
</cidade>
<cidade>
<idcidade>9611</idcidade>
<nome>Formoso do Araguaia</nome>
<idestado>27</idestado>
</cidade>
<cidade>
<idcidade>9612</idcidade>
<nome>Fortaleza do Tabocao</nome>
<idestado>27</idestado>
</cidade>
<cidade>
<idcidade>9613</idcidade>
<nome>Goianorte</nome>
<idestado>27</idestado>
</cidade>
<cidade>
<idcidade>9614</idcidade>
<nome>Goiatins</nome>
<idestado>27</idestado>
</cidade>
<cidade>
<idcidade>9615</idcidade>
<nome>Guarai</nome>
<idestado>27</idestado>
</cidade>
<cidade>
<idcidade>9616</idcidade>
<nome>Gurupi</nome>
<idestado>27</idestado>
</cidade>
<cidade>
<idcidade>9617</idcidade>
<nome>Ilha Barreira Branca</nome>
<idestado>27</idestado>
</cidade>
<cidade>
<idcidade>9618</idcidade>
<nome>Ipueiras</nome>
<idestado>27</idestado>
</cidade>
<cidade>
<idcidade>9619</idcidade>
<nome>Itacaja</nome>
<idestado>27</idestado>
</cidade>
<cidade>
<idcidade>9620</idcidade>
<nome>Itaguatins</nome>
<idestado>27</idestado>
</cidade>
<cidade>
<idcidade>9621</idcidade>
<nome>Itapiratins</nome>
<idestado>27</idestado>
</cidade>
<cidade>
<idcidade>9622</idcidade>
<nome>Itapora do Tocantins</nome>
<idestado>27</idestado>
</cidade>
<cidade>
<idcidade>9623</idcidade>
<nome>Jau do Tocantins</nome>
<idestado>27</idestado>
</cidade>
<cidade>
<idcidade>9624</idcidade>
<nome>Juarina</nome>
<idestado>27</idestado>
</cidade>
<cidade>
<idcidade>9625</idcidade>
<nome>Jussara</nome>
<idestado>27</idestado>
</cidade>
<cidade>
<idcidade>9626</idcidade>
<nome>Lagoa da Confusao</nome>
<idestado>27</idestado>
</cidade>
<cidade>
<idcidade>9627</idcidade>
<nome>Lagoa do Tocantins</nome>
<idestado>27</idestado>
</cidade>
<cidade>
<idcidade>9628</idcidade>
<nome>Lajeado</nome>
<idestado>27</idestado>
</cidade>
<cidade>
<idcidade>9629</idcidade>
<nome>Lavandeira</nome>
<idestado>27</idestado>
</cidade>
<cidade>
<idcidade>9630</idcidade>
<nome>Lizarda</nome>
<idestado>27</idestado>
</cidade>
<cidade>
<idcidade>9631</idcidade>
<nome>Luzinopolis</nome>
<idestado>27</idestado>
</cidade>
<cidade>
<idcidade>9632</idcidade>
<nome>Marianopolis do Tocantins</nome>
<idestado>27</idestado>
</cidade>
<cidade>
<idcidade>9633</idcidade>
<nome>Mateiros</nome>
<idestado>27</idestado>
</cidade>
<cidade>
<idcidade>9634</idcidade>
<nome>Maurilandia do Tocantins</nome>
<idestado>27</idestado>
</cidade>
<cidade>
<idcidade>9635</idcidade>
<nome>Miracema do Tocantins</nome>
<idestado>27</idestado>
</cidade>
<cidade>
<idcidade>9636</idcidade>
<nome>Mirandopolis</nome>
<idestado>27</idestado>
</cidade>
<cidade>
<idcidade>9637</idcidade>
<nome>Miranorte</nome>
<idestado>27</idestado>
</cidade>
<cidade>
<idcidade>9638</idcidade>
<nome>Monte do Carmo</nome>
<idestado>27</idestado>
</cidade>
<cidade>
<idcidade>9639</idcidade>
<nome>Monte Lindo</nome>
<idestado>27</idestado>
</cidade>
<cidade>
<idcidade>9640</idcidade>
<nome>Monte Santo do Tocantins</nome>
<idestado>27</idestado>
</cidade>
<cidade>
<idcidade>9641</idcidade>
<nome>Mosquito</nome>
<idestado>27</idestado>
</cidade>
<cidade>
<idcidade>9642</idcidade>
<nome>Muricilandia</nome>
<idestado>27</idestado>
</cidade>
<cidade>
<idcidade>9643</idcidade>
<nome>Natal</nome>
<idestado>27</idestado>
</cidade>
<cidade>
<idcidade>9644</idcidade>
<nome>Natividade</nome>
<idestado>27</idestado>
</cidade>
<cidade>
<idcidade>9645</idcidade>
<nome>Nazare</nome>
<idestado>27</idestado>
</cidade>
<cidade>
<idcidade>9646</idcidade>
<nome>Nova Olinda</nome>
<idestado>27</idestado>
</cidade>
<cidade>
<idcidade>9647</idcidade>
<nome>Nova Rosalandia</nome>
<idestado>27</idestado>
</cidade>
<cidade>
<idcidade>9648</idcidade>
<nome>Novo Acordo</nome>
<idestado>27</idestado>
</cidade>
<cidade>
<idcidade>9649</idcidade>
<nome>Novo Alegre</nome>
<idestado>27</idestado>
</cidade>
<cidade>
<idcidade>9650</idcidade>
<nome>Novo Horizonte</nome>
<idestado>27</idestado>
</cidade>
<cidade>
<idcidade>9651</idcidade>
<nome>Novo Jardim</nome>
<idestado>27</idestado>
</cidade>
<cidade>
<idcidade>9652</idcidade>
<nome>Oliveira de Fatima</nome>
<idestado>27</idestado>
</cidade>
<cidade>
<idcidade>9653</idcidade>
<nome>Palmas</nome>
<idestado>27</idestado>
</cidade>
<cidade>
<idcidade>9654</idcidade>
<nome>Palmeirante</nome>
<idestado>27</idestado>
</cidade>
<cidade>
<idcidade>9655</idcidade>
<nome>Palmeiropolis</nome>
<idestado>27</idestado>
</cidade>
<cidade>
<idcidade>9656</idcidade>
<nome>Paraiso do Tocantins</nome>
<idestado>27</idestado>
</cidade>
<cidade>
<idcidade>9657</idcidade>
<nome>Parana</nome>
<idestado>27</idestado>
</cidade>
<cidade>
<idcidade>9659</idcidade>
<nome>Pe da Serra</nome>
<idestado>27</idestado>
</cidade>
<cidade>
<idcidade>9660</idcidade>
<nome>Pedro Afonso</nome>
<idestado>27</idestado>
</cidade>
<cidade>
<idcidade>9661</idcidade>
<nome>Pedro Ludovico</nome>
<idestado>27</idestado>
</cidade>
<cidade>
<idcidade>9662</idcidade>
<nome>Peixe</nome>
<idestado>27</idestado>
</cidade>
<cidade>
<idcidade>9663</idcidade>
<nome>Pequizeiro</nome>
<idestado>27</idestado>
</cidade>
<cidade>
<idcidade>9664</idcidade>
<nome>Piloes</nome>
<idestado>27</idestado>
</cidade>
<cidade>
<idcidade>9665</idcidade>
<nome>Pindorama do Tocantins</nome>
<idestado>27</idestado>
</cidade>
<cidade>
<idcidade>9666</idcidade>
<nome>Piraque</nome>
<idestado>27</idestado>
</cidade>
<cidade>
<idcidade>9667</idcidade>
<nome>Pium</nome>
<idestado>27</idestado>
</cidade>
<cidade>
<idcidade>9668</idcidade>
<nome>Ponte Alta do Bom Jesus</nome>
<idestado>27</idestado>
</cidade>
<cidade>
<idcidade>9669</idcidade>
<nome>Ponte Alta do Tocantins</nome>
<idestado>27</idestado>
</cidade>
<cidade>
<idcidade>9670</idcidade>
<nome>Pontes</nome>
<idestado>27</idestado>
</cidade>
<cidade>
<idcidade>9671</idcidade>
<nome>Poraozinho</nome>
<idestado>27</idestado>
</cidade>
<cidade>
<idcidade>9672</idcidade>
<nome>Porto Alegre do Tocantins</nome>
<idestado>27</idestado>
</cidade>
<cidade>
<idcidade>9673</idcidade>
<nome>Porto Lemos</nome>
<idestado>27</idestado>
</cidade>
<cidade>
<idcidade>9674</idcidade>
<nome>Porto Nacional</nome>
<idestado>27</idestado>
</cidade>
<cidade>
<idcidade>9675</idcidade>
<nome>Praia Norte</nome>
<idestado>27</idestado>
</cidade>
<cidade>
<idcidade>9676</idcidade>
<nome>Presidente Kennedy</nome>
<idestado>27</idestado>
</cidade>
<cidade>
<idcidade>9677</idcidade>
<nome>Principe</nome>
<idestado>27</idestado>
</cidade>
<cidade>
<idcidade>9678</idcidade>
<nome>Pugmil</nome>
<idestado>27</idestado>
</cidade>
<cidade>
<idcidade>9679</idcidade>
<nome>Recursolandia</nome>
<idestado>27</idestado>
</cidade>
<cidade>
<idcidade>9680</idcidade>
<nome>Riachinho</nome>
<idestado>27</idestado>
</cidade>
<cidade>
<idcidade>9681</idcidade>
<nome>Rio da Conceicao</nome>
<idestado>27</idestado>
</cidade>
<cidade>
<idcidade>9682</idcidade>
<nome>Rio dos Bois</nome>
<idestado>27</idestado>
</cidade>
<cidade>
<idcidade>9683</idcidade>
<nome>Rio Sono</nome>
<idestado>27</idestado>
</cidade>
<cidade>
<idcidade>9684</idcidade>
<nome>Sampaio</nome>
<idestado>27</idestado>
</cidade>
<cidade>
<idcidade>9685</idcidade>
<nome>Sandolandia</nome>
<idestado>27</idestado>
</cidade>
<cidade>
<idcidade>9686</idcidade>
<nome>Santa Fe do Araguaia</nome>
<idestado>27</idestado>
</cidade>
<cidade>
<idcidade>9687</idcidade>
<nome>Santa Maria do Tocantins</nome>
<idestado>27</idestado>
</cidade>
<cidade>
<idcidade>9688</idcidade>
<nome>Santa Rita do Tocantins</nome>
<idestado>27</idestado>
</cidade>
<cidade>
<idcidade>9689</idcidade>
<nome>Santa Rosa do Tocantins</nome>
<idestado>27</idestado>
</cidade>
<cidade>
<idcidade>9690</idcidade>
<nome>Santa Tereza do Tocantins</nome>
<idestado>27</idestado>
</cidade>
<cidade>
<idcidade>9691</idcidade>
<nome>Santa Terezinha do Tocantins</nome>
<idestado>27</idestado>
</cidade>
<cidade>
<idcidade>9692</idcidade>
<nome>Sao Bento do Tocantins</nome>
<idestado>27</idestado>
</cidade>
<cidade>
<idcidade>9693</idcidade>
<nome>Sao Felix do Tocantins</nome>
<idestado>27</idestado>
</cidade>
<cidade>
<idcidade>9694</idcidade>
<nome>Sao Miguel do Tocantins</nome>
<idestado>27</idestado>
</cidade>
<cidade>
<idcidade>9695</idcidade>
<nome>Sao Salvador do Tocantins</nome>
<idestado>27</idestado>
</cidade>
<cidade>
<idcidade>9696</idcidade>
<nome>Sao Sebastiao do Tocantins</nome>
<idestado>27</idestado>
</cidade>
<cidade>
<idcidade>9697</idcidade>
<nome>Sao Valerio da Natividade</nome>
<idestado>27</idestado>
</cidade>
<cidade>
<idcidade>9698</idcidade>
<nome>Silvanopolis</nome>
<idestado>27</idestado>
</cidade>
<cidade>
<idcidade>9699</idcidade>
<nome>Sitio Novo do Tocantins</nome>
<idestado>27</idestado>
</cidade>
<cidade>
<idcidade>9700</idcidade>
<nome>Sucupira</nome>
<idestado>27</idestado>
</cidade>
<cidade>
<idcidade>9701</idcidade>
<nome>Taguatinga</nome>
<idestado>27</idestado>
</cidade>
<cidade>
<idcidade>9702</idcidade>
<nome>Taipas do Tocantins</nome>
<idestado>27</idestado>
</cidade>
<cidade>
<idcidade>9703</idcidade>
<nome>Talisma</nome>
<idestado>27</idestado>
</cidade>
<cidade>
<idcidade>9704</idcidade>
<nome>Tamboril</nome>
<idestado>27</idestado>
</cidade>
<cidade>
<idcidade>9705</idcidade>
<nome>Taquaralto</nome>
<idestado>27</idestado>
</cidade>
<cidade>
<idcidade>9706</idcidade>
<nome>Taquarussu do Tocantins</nome>
<idestado>27</idestado>
</cidade>
<cidade>
<idcidade>9707</idcidade>
<nome>Tocantinia</nome>
<idestado>27</idestado>
</cidade>
<cidade>
<idcidade>9708</idcidade>
<nome>Tocantinopolis</nome>
<idestado>27</idestado>
</cidade>
<cidade>
<idcidade>9709</idcidade>
<nome>Tupirama</nome>
<idestado>27</idestado>
</cidade>
<cidade>
<idcidade>9710</idcidade>
<nome>Tupirata</nome>
<idestado>27</idestado>
</cidade>
<cidade>
<idcidade>9711</idcidade>
<nome>Tupiratins</nome>
<idestado>27</idestado>
</cidade>
<cidade>
<idcidade>9712</idcidade>
<nome>Venus</nome>
<idestado>27</idestado>
</cidade>
<cidade>
<idcidade>9713</idcidade>
<nome>Wanderlandia</nome>
<idestado>27</idestado>
</cidade>
<cidade>
<idcidade>9714</idcidade>
<nome>Xambioa</nome>
<idestado>27</idestado>
</cidade>
</cidades>
